setup.cfg
setup.py
bin/daemon.py
twitter_dedupe.egg-info/PKG-INFO
twitter_dedupe.egg-info/SOURCES.txt
twitter_dedupe.egg-info/dependency_links.txt
twitter_dedupe.egg-info/not-zip-safe
twitter_dedupe.egg-info/requires.txt
twitter_dedupe.egg-info/top_level.txt
twitterdedupe/__init__.py
twitterdedupe/app.py
twitterdedupe/caches.py
twitterdedupe/daemons.py
twitterdedupe/tests/__init__.py
twitterdedupe/tests/helpers.py
twitterdedupe/tests/test_consider_status.py
twitterdedupe/tests/test_get_my_unique.py
twitterdedupe/tests/test_get_since_id.py
twitterdedupe/tests/test_lengthen_url.py