Metadata-Version: 1.1
Name: twitter-dedupe
Version: 0.6.1
Summary: Python library to retweet unique links from noisy Twitter accounts.
Home-page: https://github.com/cmheisel/twitter-dedupe
Author: Chris Heisel
Author-email: chris@heisel.org
License: UNKNOWN
Platform: UNKNOWN
Classifier: Environment :: Web Environment
Classifier: Intended Audience :: Developers
Classifier: Operating System :: OS Independent
Classifier: Programming Language :: Python
Classifier: Topic :: Internet :: WWW/HTTP :: Dynamic Content
